LICENSE
README.rst
pyproject.toml
kirk.egg-info/PKG-INFO
kirk.egg-info/SOURCES.txt
kirk.egg-info/dependency_links.txt
kirk.egg-info/entry_points.txt
kirk.egg-info/requires.txt
kirk.egg-info/top_level.txt
libkirk/__init__.py
libkirk/com.py
libkirk/data.py
libkirk/errors.py
libkirk/evt.py
libkirk/export.py
libkirk/framework.py
libkirk/io.py
libkirk/ltp.py
libkirk/main.py
libkirk/monitor.py
libkirk/plugin.py
libkirk/results.py
libkirk/scheduler.py
libkirk/session.py
libkirk/sut.py
libkirk/sut_base.py
libkirk/tempfile.py
libkirk/types.py
libkirk/ui.py