Metadata-Version: 2.4
Name: kirk
Version: 3.0
Summary: Linux Test Project tests executor
Author-email: Linux Test Project <ltp@lists.linux.it>
Maintainer-email: Andrea Cervesato <andrea.cervesato@suse.com>
License:                     GNU GENERAL PUBLIC LICENSE
Project-URL: Homepage, https://github.com/linux-test-project/kirk
Project-URL: Bug Reports, https://github.com/linux-test-project/kirk/issues
Keywords: testing,linux,development,ltp,linux-test-project
Classifier: Natural Language :: English
Classifier: Intended Audience :: Developers
Classifier: Operating System :: OS Independent
Classifier: Programming Language :: Python
Classifier: Programming Language :: Python :: 3.6
Classifier: Programming Language :: Python :: 3.7
Classifier: Programming Language :: Python :: 3.8
Classifier: Programming Language :: Python :: 3.9
Classifier: Programming Language :: Python :: 3.10
Classifier: Programming Language :: Python :: 3.11
Classifier: Programming Language :: Python :: 3.12
Classifier: Programming Language :: Python :: 3.13
Classifier: Programming Language :: Python :: 3.14
Classifier: Topic :: Software Development :: Testing
Requires-Python: >=3.6
License-File: LICENSE
Provides-Extra: ssh
Requires-Dist: asyncssh<=2.17.0; extra == "ssh"
Provides-Extra: ltx
Requires-Dist: msgpack<=1.1.0; extra == "ltx"
Dynamic: license-file
